{
  "assistedTicketCoverageCities": [
    "Shenzhen"
  ],
  "cityEventCounts": {
    "Boom": 2,
    "Daresbury": 1,
    "Las Vegas": 2,
    "Miami": 1,
    "Orlando": 1,
    "Salmo": 1,
    "Shenzhen": 16,
    "Vancouver": 56
  },
  "directTicketCoverageLimited": true,
  "directTicketCoverageLimitedCities": [
    "Shenzhen"
  ],
  "eventCount": 80,
  "executionLane": "githubHTML",
  "feedPath": "feed/v1/feed.draft.json",
  "feedSHA256": "d8437197ebdb2be8356cc6668e853318dddd3a64ac131b2f32c46069ecfa699c",
  "inactiveRetainedEventCount": 0,
  "inactiveSourceCount": 5,
  "inactiveSourceIDs": [
    "am06_wechat",
    "atmos_wechat",
    "oil_wechat",
    "sauce_wechat",
    "yuyuan_miniprogram"
  ],
  "ingestRunAt": "2026-07-17T17:48:03Z",
  "ingestRunId": "9CABC221-254B-416E-BD01-211EFA9F5274",
  "publicationGateStatus": "ready",
  "publishedAt": "2026-07-17T17:52:11Z",
  "reportPath": "report/ingest_report.json",
  "reportSHA256": "aa9558babde6c51062e5d4334ae3ea4b3c36952ba4a51f144c948a81c4f6186e",
  "schemaVersion": 1,
  "sourceCommitSHA": "b63d41ceef52cbcb7e310cce9fc7352755c0e91f",
  "sourceCoverageStatus": "partial",
  "sourceRepository": "roik378/RaverMVP",
  "status": "ready",
  "ticketCoverageLimited": false,
  "ticketCoverageLimitedCities": [],
  "ticketEnrichmentStatus": "applied",
  "ticketPriceProjectionSHA256": "a781974c93fa2a0f7d51ccd459250ddce0ab577af4603d5678c3b6989254f61f",
  "ticketPriceReceiptPath": "report/ticket_price_snapshot_receipt.json",
  "ticketPriceReceiptSHA256": "1d0a51937ab1ccb13be993900c6ad962adee3e83a3c90b80e54070f2ce83743f",
  "ticketQualityGateStatus": "ready",
  "ticketReceiptPath": "report/ticket_enrichment_receipt.json",
  "ticketReceiptSHA256": "74cf88699e274ee462f05e94fcbdb461b0d22bb3beaa3afdf4b57cade5296668"
}
